schiebung/__init__.py
schiebung/schiebung.cpython-313t-s390x-linux-gnu.so
schiebung-0.2.0.dist-info/METADATA
schiebung-0.2.0.dist-info/WHEEL
schiebung-0.2.0.dist-info/RECORD
