Metadata-Version: 2.4
Name: schiebung
Version: 0.2.0
Summary: Python bindings for the schiebung core library
Keywords: robotics,transform
Author: Michael Maerz
License: MIT
Requires-Python: >=3.8
Project-URL: Bug Tracker, https://github.com/MaxiMaerz/schiebung/issues
Project-URL: Homepage, https://github.com/MaxiMaerz/schiebung/
Project-URL: Repository, https://github.com/MaxiMaerz/schiebung/
